camaraPy/__init__.py
camaraPy/api_original/__init__.py
camaraPy/api_original/deputados.py
camaraPy/api_original/orgaos.py
camaraPy/api_original/proposicoes.py
camaraPy/api_original/sessoes_reunioes.py
camaraPy/api_original/core/__init__.py
camaraPy/api_original/core/core.py
camaraPy/api_original/core/custom_exceptions.py
camaraPy-0.0.5.dist-info/LICENSE
camaraPy-0.0.5.dist-info/METADATA
camaraPy-0.0.5.dist-info/WHEEL
camaraPy-0.0.5.dist-info/top_level.txt
camaraPy-0.0.5.dist-info/RECORD
