Metadata-Version: 2.1
Name: camaraPy
Version: 0.0.5
Summary: A wrapper for the Brazilian House of Representatives public data API
Home-page: https://github.com/RodrigoMenegat/camaraPy
Author: Rodrigo Menegat Schuinski
Author-email: rodrigoschuinski@gmail.com
License: UNKNOWN
Platform: UNKNOWN
Classifier: Programming Language :: Python :: 3
Classifier: License :: OSI Approved :: GNU General Public License (GPL)
Classifier: Operating System :: Unix
Requires-Python: >=3.6
Requires-Dist: requests (>=2.21.0)
Requires-Dist: xmltodict (>=0.12.0)
